{
  "isMusician": false,
  "userId": -1,
  "topComments": [],
  "moreHot": true,
  "comments":[
    {
      "user": {
        "authStatus": 0,
        "avatarUrl": "https://p1.music.126.net/F2iEV_ewaNeRVkZd3WKrtA==/109951164068369247.jpg",
        "expertTags": null,
        "experts": null,
        "liveInfo": null,
        "locationInfo": null,
        "nickname": "Pati1900",
        "remarkName": null,
        "userId": 17295810,
        "userType": 0,
        "vipRights": null,
        "vipType": 10
      },
      "beReplied": [
        {
          "beRepliedCommentId": 6849824,
          "content": "第一次听这首歌是在爸爸打开的收音机里，那时我在阳光里睁开眼听到了第一句。七年过去了，大家变成自己喜欢的样子了吗[开心]",
          "expressionUrl": null,
          "status": 0,
          "user":{
            "authStatus": 0,
            "avatarUrl": "https://p1.music.126.net/F2iEV_ewaNeRVkZd3WKrtA==/109951164068369247.jpg",
            "expertTags": null,
            "experts": null,
            "liveInfo": null,
            "locationInfo": null,
            "nickname": "Pati1900",
            "remarkName": null,
            "userId": 17295810,
            "userType": 0,
            "vipRights": null,
            "vipType": 10
          }
        }
      ],
      "pendantData": null,
      "showFloorComment": null,
      "status": 0,
      "commentId": 8125198,
      "content": "这曲这么清新竟然不红我很心痛啊！！",
      "time": 1420296330491,
      "likedCount": 52907,
      "expressionUrl": null,
      "commentLocationType": 0,
      "parentCommentId": 0,
      "decoration": null,
      "repliedMark": false,
      "liked": false
    },
    {
      "user": {
        "authStatus": 0,
        "avatarUrl": "https://p1.music.126.net/F2iEV_ewaNeRVkZd3WKrtA==/109951164068369247.jpg",
        "expertTags": null,
        "experts": null,
        "liveInfo": null,
        "locationInfo": null,
        "nickname": "Pati1900",
        "remarkName": null,
        "userId": 17295810,
        "userType": 0,
        "vipRights": null,
        "vipType": 10
      },
      "beReplied": [
        {
          "beRepliedCommentId": 6849824,
          "content": "第一次听这首歌是在爸爸打开的收音机里，那时我在阳光里睁开眼听到了第一句。七年过去了，大家变成自己喜欢的样子了吗[开心]",
          "expressionUrl": null,
          "status": 0,
          "user":{
            "authStatus": 0,
            "avatarUrl": "https://p1.music.126.net/F2iEV_ewaNeRVkZd3WKrtA==/109951164068369247.jpg",
            "expertTags": null,
            "experts": null,
            "liveInfo": null,
            "locationInfo": null,
            "nickname": "Pati1900",
            "remarkName": null,
            "userId": 17295810,
            "userType": 0,
            "vipRights": null,
            "vipType": 10
          }
        }
      ],
      "pendantData": null,
      "showFloorComment": null,
      "status": 0,
      "commentId": 8125198,
      "content": "这曲这么清新竟然不红我很心痛啊！！",
      "time": 1420296330491,
      "likedCount": 52907,
      "expressionUrl": null,
      "commentLocationType": 0,
      "parentCommentId": 0,
      "decoration": null,
      "repliedMark": false,
      "liked": false
    }
  ],
  "hotComments": [
    {
      "user": {
        "authStatus": 0,
        "avatarUrl": "https://p1.music.126.net/F2iEV_ewaNeRVkZd3WKrtA==/109951164068369247.jpg",
        "expertTags": null,
        "experts": null,
        "liveInfo": null,
        "locationInfo": null,
        "nickname": "Pati1900",
        "remarkName": null,
        "userId": 17295810,
        "userType": 0,
        "vipRights": null,
        "vipType": 10
      },
      "beReplied": [
        {
          "beRepliedCommentId": 6849824,
          "content": "第一次听这首歌是在爸爸打开的收音机里，那时我在阳光里睁开眼听到了第一句。七年过去了，大家变成自己喜欢的样子了吗[开心]",
          "expressionUrl": null,
          "status": 0,
          "user":{
            "authStatus": 0,
            "avatarUrl": "https://p1.music.126.net/F2iEV_ewaNeRVkZd3WKrtA==/109951164068369247.jpg",
            "expertTags": null,
            "experts": null,
            "liveInfo": null,
            "locationInfo": null,
            "nickname": "Pati1900",
            "remarkName": null,
            "userId": 17295810,
            "userType": 0,
            "vipRights": null,
            "vipType": 10
          }
        }
      ],
      "pendantData": null,
      "showFloorComment": null,
      "status": 0,
      "commentId": 8125198,
      "content": "这曲这么清新竟然不红我很心痛啊！！",
      "time": 1420296330491,
      "likedCount": 52907,
      "expressionUrl": null,
      "commentLocationType": 0,
      "parentCommentId": 0,
      "decoration": null,
      "repliedMark": false,
      "liked": false
    },
    {
      "user": {
        "authStatus": 0,
        "avatarUrl": "https://p1.music.126.net/F2iEV_ewaNeRVkZd3WKrtA==/109951164068369247.jpg",
        "expertTags": null,
        "experts": null,
        "liveInfo": null,
        "locationInfo": null,
        "nickname": "Pati1900",
        "remarkName": null,
        "userId": 17295810,
        "userType": 0,
        "vipRights": null,
        "vipType": 10
      },
      "beReplied": [
        {
          "beRepliedCommentId": 6849824,
          "content": "第一次听这首歌是在爸爸打开的收音机里，那时我在阳光里睁开眼听到了第一句。七年过去了，大家变成自己喜欢的样子了吗[开心]",
          "expressionUrl": null,
          "status": 0,
          "user":{
            "authStatus": 0,
            "avatarUrl": "https://p1.music.126.net/F2iEV_ewaNeRVkZd3WKrtA==/109951164068369247.jpg",
            "expertTags": null,
            "experts": null,
            "liveInfo": null,
            "locationInfo": null,
            "nickname": "Pati1900",
            "remarkName": null,
            "userId": 17295810,
            "userType": 0,
            "vipRights": null,
            "vipType": 10
          }
        }
      ],
      "pendantData": null,
      "showFloorComment": null,
      "status": 0,
      "commentId": 8125198,
      "content": "这曲这么清新竟然不红我很心痛啊！！",
      "time": 1420296330491,
      "likedCount": 52907,
      "expressionUrl": null,
      "commentLocationType": 0,
      "parentCommentId": 0,
      "decoration": null,
      "repliedMark": false,
      "liked": false
    }
  ],
  "total": 28762,
  "more": true
}